pino/__init__.py
pino/core.py
pino/pretty_cli.py
pino/utils.py
pino-0.6.0.dist-info/entry_points.txt
pino-0.6.0.dist-info/LICENSE
pino-0.6.0.dist-info/WHEEL
pino-0.6.0.dist-info/METADATA
pino-0.6.0.dist-info/RECORD
