Metadata-Version: 2.1
Name: pino
Version: 0.6.0
Summary: Python json logger inspired by pino.js
Home-page: https://github.com/CoorpAcademy/pino.py
License: MIT
Keywords: log,logger,logging,json
Author: Adrien Becchis
Author-email: adrien.becchis@coorpacademy.com
Requires-Python: >=3.6,<4.0
Classifier: Development Status :: 4 - Beta
Classifier: Environment :: Console
Classifier: Intended Audience :: Developers
Classifier: License :: OSI Approved :: MIT License
Classifier: Operating System :: OS Independent
Classifier: Programming Language :: Python
Classifier: Programming Language :: Python :: 3
Classifier: Programming Language :: Python :: 3.6
Classifier: Programming Language :: Python :: 3.7
Classifier: Programming Language :: Python :: 3.8
Classifier: Programming Language :: Python :: 3.9
Classifier: Programming Language :: Python :: Implementation :: PyPy
Classifier: Topic :: Software Development :: Libraries :: Python Modules
Classifier: Topic :: System :: Logging
Requires-Dist: style (>=1.1.6,<2.0.0)
